fondi/__init__.py
fondi/fileloader.py
fondi/mathtext.py
fondi/layout/__init__.py
fondi/layout/cases.py
fondi/layout/decoration.py
fondi/layout/fraction.py
fondi/layout/helper.py
fondi/layout/ignore.py
fondi/layout/integral.py
fondi/layout/layout.py
fondi/layout/parenthesis.py
fondi/layout/spaces.py
fondi/layout/sqrt.py
fondi/layout/supersub.py
fondi/layout/symbols.py
fondi/layout/text.py
fondi/parser/__init__.py
fondi/parser/helper.py
fondi/parser/parser.py
fondi/parser/tokens.py
fondi/plain/__init__.py
fondi/plain/helper.py
fondi/plain/image.py
fondi/plain/plain.py
fondi/plain/symbol.py
fondi/resources/NewCM10-Italic.otf
fondi/resources/NewCM10-Regular.otf
fondi/resources/__init__.py
fondi/resources/cmu.serif-roman.ttf
fondi/resources/contour-integral.png
fondi/resources/integral.png
fondi/resources/normpara_left.png
fondi/resources/normpara_right.png
fondi/resources/tuborpara_left.png
fondi/resources/tuborpara_right.png
fondi/resources/fonts/NewCM08-Book.otf
fondi/resources/fonts/NewCM08-BookItalic.otf
fondi/resources/fonts/NewCM08-Italic.otf
fondi/resources/fonts/NewCM08-Regular.otf
fondi/resources/fonts/NewCM08Devanagari-Book.otf
fondi/resources/fonts/NewCM08Devanagari-Regular.otf
fondi/resources/fonts/NewCM10-Bold.otf
fondi/resources/fonts/NewCM10-BoldItalic.otf
fondi/resources/fonts/NewCM10-Book.otf
fondi/resources/fonts/NewCM10-BookItalic.otf
fondi/resources/fonts/NewCM10-Italic.otf
fondi/resources/fonts/NewCM10-Regular.otf
fondi/resources/fonts/NewCM10Devanagari-Bold.otf
fondi/resources/fonts/NewCM10Devanagari-Book.otf
fondi/resources/fonts/NewCM10Devanagari-Regular.otf
fondi/resources/fonts/NewCMMath-Book.otf
fondi/resources/fonts/NewCMMath-Regular.otf
fondi/resources/fonts/NewCMMono10-Bold.otf
fondi/resources/fonts/NewCMMono10-BoldOblique.otf
fondi/resources/fonts/NewCMMono10-Book.otf
fondi/resources/fonts/NewCMMono10-BookItalic.otf
fondi/resources/fonts/NewCMMono10-Italic.otf
fondi/resources/fonts/NewCMMono10-Regular.otf
fondi-0.1.6.dist-info/licenses/LICENSE
fondi-0.1.6.dist-info/METADATA
fondi-0.1.6.dist-info/WHEEL
fondi-0.1.6.dist-info/top_level.txt
fondi-0.1.6.dist-info/RECORD
