Metadata-Version: 2.4
Name: fondi
Version: 0.1.6
Summary: A small rendering for LaTeX mathematics
Author-email: Valter Yde Daugberg <valteryde@hotmail.com>
Project-URL: Homepage, https://github.com/valteryde/fondi
Project-URL: Issues, https://github.com/valteryde/fondi/issues
Classifier: Programming Language :: Python :: 3
Classifier: License :: OSI Approved :: GNU General Public License v3 (GPLv3)
Classifier: Operating System :: OS Independent
Requires-Python: >=3.8
License-File: LICENSE
Requires-Dist: pillow
Dynamic: license-file
